hunny/__init__.py
hunny/hunny.py
hunny/version.py
hunny/package_name/__init__.py
hunny/package_name/hunny.py
hunny/package_name/version.py
hunny-0.0.1b0.dist-info/LICENSE
hunny-0.0.1b0.dist-info/METADATA
hunny-0.0.1b0.dist-info/WHEEL
hunny-0.0.1b0.dist-info/top_level.txt
hunny-0.0.1b0.dist-info/RECORD
