Metadata-Version: 2.2
Name: hunny
Version: 0.0.1b0
Summary: hunny
Author-email: "Rodrigo Martínez (brunneis)" <dev@brunneis.com>
License: GNU General Public License v3 (GPLv3)
Project-URL: Homepage, https://github.com/labteral/hunny
Classifier: Development Status :: 4 - Beta
Classifier: Environment :: Console
Classifier: Intended Audience :: Developers
Classifier: License :: OSI Approved :: GNU General Public License v3 (GPLv3)
Classifier: Operating System :: POSIX :: Linux
Classifier: Programming Language :: Python :: 3.10
Classifier: Programming Language :: Python :: Implementation :: PyPy
Classifier: Topic :: Software Development :: Libraries :: Python Modules
Requires-Python: >=3.10
License-File: LICENSE
